in_toto/__init__.py
in_toto/common_args.py
in_toto/exceptions.py
in_toto/formats.py
in_toto/in_toto_match_products.py
in_toto/in_toto_mock.py
in_toto/in_toto_record.py
in_toto/in_toto_run.py
in_toto/in_toto_sign.py
in_toto/in_toto_verify.py
in_toto/log.py
in_toto/rulelib.py
in_toto/runlib.py
in_toto/settings.py
in_toto/verifylib.py
in_toto/models/__init__.py
in_toto/models/_signer.py
in_toto/models/common.py
in_toto/models/layout.py
in_toto/models/link.py
in_toto/models/metadata.py
in_toto/resolver/__init__.py
in_toto/resolver/_resolver.py
in_toto-3.0.0.dist-info/METADATA
in_toto-3.0.0.dist-info/WHEEL
in_toto-3.0.0.dist-info/entry_points.txt
in_toto-3.0.0.dist-info/licenses/LICENSE
in_toto-3.0.0.dist-info/RECORD
