Metadata-Version: 2.3
Name: in-toto
Version: 3.0.0
Summary: A framework to define and secure the integrity of software supply chains
Project-URL: Bug Reports, https://github.com/in-toto/in-toto/issues
Project-URL: Homepage, https://in-toto.io
Project-URL: Source, https://github.com/in-toto/in-toto
Author-email: "New York University: Secure Systems Lab" <in-toto-dev@googlegroups.com>
License-Expression: Apache-2.0
License-File: LICENSE
Keywords: security,software,supply chain
Classifier: Development Status :: 5 - Production/Stable
Classifier: Intended Audience :: Developers
Classifier: License :: OSI Approved :: Apache Software License
Classifier: Natural Language :: English
Classifier: Operating System :: MacOS :: MacOS X
Classifier: Operating System :: POSIX
Classifier: Operating System :: POSIX :: Linux
Classifier: Programming Language :: Python
Classifier: Programming Language :: Python :: 3
Classifier: Programming Language :: Python :: 3.8
Classifier: Programming Language :: Python :: 3.9
Classifier: Programming Language :: Python :: 3.10
Classifier: Programming Language :: Python :: 3.11
Classifier: Programming Language :: Python :: Implementation :: CPython
Classifier: Topic :: Security
Classifier: Topic :: Software Development
Requires-Python: ~=3.8
Requires-Dist: attrs
Requires-Dist: iso8601
Requires-Dist: pathspec
Requires-Dist: python-dateutil
Requires-Dist: securesystemslib[crypto]~=1.0
